README.txt
setup.py
Products/__init__.py
Products.PortalTaxonomy.egg-info/PKG-INFO
Products.PortalTaxonomy.egg-info/SOURCES.txt
Products.PortalTaxonomy.egg-info/dependency_links.txt
Products.PortalTaxonomy.egg-info/entry_points.txt
Products.PortalTaxonomy.egg-info/namespace_packages.txt
Products.PortalTaxonomy.egg-info/not-zip-safe
Products.PortalTaxonomy.egg-info/requires.txt
Products.PortalTaxonomy.egg-info/top_level.txt
Products/PortalTaxonomy/ContentInitHack.py
Products/PortalTaxonomy/CustomizationPolicy.py
Products/PortalTaxonomy/Permissions.py
Products/PortalTaxonomy/__init__.py
Products/PortalTaxonomy/refresh.txt
Products/PortalTaxonomy/tool.gif
Products/PortalTaxonomy/version.txt
Products/PortalTaxonomy/Extensions/Install.py
Products/PortalTaxonomy/Extensions/__init__.py
Products/PortalTaxonomy/content/AttributeManager.py
Products/PortalTaxonomy/content/CategoryManager.py
Products/PortalTaxonomy/content/__init__.py
Products/PortalTaxonomy/content/schemata.py
Products/PortalTaxonomy/examples/TaxonomyType.py
Products/PortalTaxonomy/examples/__init__.py
Products/PortalTaxonomy/fields/AttributeField.py
Products/PortalTaxonomy/fields/CategoryField.py
Products/PortalTaxonomy/fields/__init__.py
Products/PortalTaxonomy/interfaces/ICategorizable.py
Products/PortalTaxonomy/interfaces/__init__.py
Products/PortalTaxonomy/skins/PortalTaxonomy/arrow.gif
Products/PortalTaxonomy/skins/PortalTaxonomy/arrowon.gif
Products/PortalTaxonomy/skins/PortalTaxonomy/attribute.gif
Products/PortalTaxonomy/skins/PortalTaxonomy/attribute_utilities.pt
Products/PortalTaxonomy/skins/PortalTaxonomy/attribute_widget.pt
Products/PortalTaxonomy/skins/PortalTaxonomy/attributecollection.gif
Products/PortalTaxonomy/skins/PortalTaxonomy/attributemanager.gif
Products/PortalTaxonomy/skins/PortalTaxonomy/batch_attributes.pt
Products/PortalTaxonomy/skins/PortalTaxonomy/batch_attributes_process.py
Products/PortalTaxonomy/skins/PortalTaxonomy/batch_categories.pt
Products/PortalTaxonomy/skins/PortalTaxonomy/batch_categories_process.py
Products/PortalTaxonomy/skins/PortalTaxonomy/category.gif
Products/PortalTaxonomy/skins/PortalTaxonomy/category_content.pt
Products/PortalTaxonomy/skins/PortalTaxonomy/category_content_recursive.pt
Products/PortalTaxonomy/skins/PortalTaxonomy/category_default.pt
Products/PortalTaxonomy/skins/PortalTaxonomy/category_list.pt
