Metadata-Version: 1.0
Name: Products.PortalTaxonomy
Version: 0.5.0
Summary: Provides a way to create a treeish category structure and then limit the association of content instances to specific sections of the tree.
Home-page: http://plone.org/products/portal_taxonomy
Author: Jeremy Stark
Author-email: jeremy@deximer.com
License: GPL
Keywords: Plone,Taxonomy
Platform: UNKNOWN
Classifier: Programming Language :: Python
Classifier: Topic :: Software Development :: Libraries :: Python Modules
